pymcef-0.2.8.data/purelib/pymcef/__init__.py
pymcef-0.2.8.data/purelib/pymcef/_ppslp.pyd
pymcef-0.2.8.data/purelib/pymcef/ppslp.py
pymcef-0.2.8.data/purelib/pymcef/simple.py
pymcef-0.2.8.data/purelib/pymcef/simple_plot.py
pymcef-0.2.8.data/purelib/pymcef/tests/__init__.py
pymcef-0.2.8.data/purelib/pymcef/tests/test_all.py
pymcef-0.2.8.data/purelib/pymcef/tests/test_ppslp.py
pymcef-0.2.8.data/purelib/pymcef/tests/test_pymcef.py
pymcef-0.2.8.data/purelib/pymcef/tests/output/abs_semi_dev/placeholder
pymcef-0.2.8.data/purelib/pymcef/tests/output/fixed_targ_und/placeholder
pymcef-0.2.8.dist-info/DESCRIPTION.rst
pymcef-0.2.8.dist-info/METADATA
pymcef-0.2.8.dist-info/RECORD
pymcef-0.2.8.dist-info/WHEEL
pymcef-0.2.8.dist-info/metadata.json
pymcef-0.2.8.dist-info/top_level.txt
