Metadata-Version: 2.0
Name: pymcef
Version: 0.2.8
Summary: Efficient frontier based on Monte Carlo simulated returns
Home-page: https://github.com/hzzyyy/pymcef
Author: Zhangyi(Zane) Hu
Author-email: hu.zhangyi@gmail.com
License: BSD
Requires-Dist: matplotlib
Requires-Dist: numpy
